{
  "schemaVersion": "1.0",
  "manufacturer": "Xiaomi",
  "models": ["lumi.switch.b1nacn02", "lumi.switch.b2nacn02"],
  "description": "Xiaomi Aqara D1 1-gang QBKG23LM and 2-gang QBKG24LM with neutral wire (2020 version)",
  "buttons": [
    {
      "name": "Button 1",
      "eventMap": {
        "1002": "SINGLE_PRESS",
        "1003": "LONG_PRESS",
        "1004": "DOUBLE_PRESS"
      }
    },
    {
      "name": "Button 2",
      "eventMap": {
        "2002": "SINGLE_PRESS",
        "2003": "LONG_PRESS",
        "2004": "DOUBLE_PRESS"
      }
    },
    {
      "name": "Button 3",
      "eventMap": {
        "3002": "SINGLE_PRESS",
        "3003": "LONG_PRESS",
        "3004": "DOUBLE_PRESS"
      }
    }
  ]
}
